setup.py
volleyup/__init__.py
volleyup.egg-info/PKG-INFO
volleyup.egg-info/SOURCES.txt
volleyup.egg-info/dependency_links.txt
volleyup.egg-info/requires.txt
volleyup.egg-info/top_level.txt