Metadata-Version: 1.0
Name: volleyup
Version: 0.1
Summary: Beach Volleyball Match Analysis
Home-page: http://github.com/jinified/volleyup/
Author: Jin
Author-email: jinified@gmail.com
License: MIT
Keywords: tracking detection volleyball
Platform: UNKNOWN
